MANIFEST.in
README.md
setup.cfg
setup.py
printtable/__init__.py
printtable/printtable.py
printtable.egg-info/PKG-INFO
printtable.egg-info/SOURCES.txt
printtable.egg-info/dependency_links.txt
printtable.egg-info/top_level.txt
tests/__init__.py
tests/test.py
tests/test_chi.py