Metadata-Version: 1.0
Name: printtable
Version: 1.2
Summary: a library for drawing the table in the terminal
Home-page: https://github.com/prozhuchen/PrintTable
Author: prozhuchen
Author-email: prozhuchen@gmail.com
License: MIT License
Keywords: print table
Platform: any
